{
  "EventTime": "2020-02-21T01:20:26.439683-08:00",
  "Hostname": "WIN-CIR2AVVLRU2",
  "Keywords": "9232379236109516800",
  "EventType": "AUDIT_SUCCESS",
  "SeverityValue": 2,
  "Severity": "INFO",
  "EventID": 5156,
  "SourceName": "Microsoft-Windows-Security-Auditing",
  "ProviderGuid": "{54849625-5478-4994-A5BA-3E3B0328C30D}",
  "Version": 1,
  "TaskValue": 12810,
  "OpcodeValue": 0,
  "RecordNumber": 1347,
  "ExecutionProcessID": 4,
  "ExecutionThreadID": 232,
  "Channel": "Security",
  "Message": "The Windows Filtering Platform has permitted a connection.\r\n\r\nApplication Information:\r\n\tProcess ID:\t\t4\r\n\tApplication Name:\tSystem\r\n\r\nNetwork Information:\r\n\tDirection:\t\tOutbound\r\n\tSource Address:\t\t192.168.171.148\r\n\tSource Port:\t\t8\r\n\tDestination Address:\t188.23.1.43\r\n\tDestination Port:\t\t0\r\n\tProtocol:\t\t1\r\n\r\nFilter Information:\r\n\tFilter Run-Time ID:\t72414\r\n\tLayer Name:\t\tConnect\r\n\tLayer Run-Time ID:\t48",
  "Category": "Filtering Platform Connection",
  "Opcode": "Info",
  "ProcessID": "4",
  "Application": "System",
  "Direction": "%%14593",
  "SourceAddress": "192.168.171.1",
  "SourcePort": "8",
  "DestAddress": "188.23.1.43",
  "DestPort": "0",
  "Protocol": "1",
  "FilterRTID": "72414",
  "LayerName": "%%14611",
  "LayerRTID": "48",
  "RemoteUserID": "S-1-0-0",
  "RemoteMachineID": "S-1-0-0",
  "EventReceivedTime": "2020-02-21T01:20:27.818729-08:00",
  "SourceModuleName": "in_win",
  "SourceModuleType": "im_msvistalog"
}